setup.cfg
setup.py
opencache/__init__.py
opencache/lib/__init__.py
opencache/lib/opencachelib.py
opencache_lib.egg-info/PKG-INFO
opencache_lib.egg-info/SOURCES.txt
opencache_lib.egg-info/dependency_links.txt
opencache_lib.egg-info/namespace_packages.txt
opencache_lib.egg-info/top_level.txt