Metadata-Version: 1.1
Name: opencache-lib
Version: 0.1.0
Summary: Shared code between the OpenCache Node and Controller.
Home-page: https://github.com/opencache-project/opencache-lib
Author: Matthew Broadbent
Author-email: matt@matthewbroadbent.net
License: Apache License, Version 2.0
Download-URL: https://github.com/opencache-project/opencache-lib/tarball/0.1.0
Keywords: content,caching,distribution,software defined networking
Platform: UNKNOWN
Classifier: Development Status :: 3 - Alpha
Classifier: Intended Audience :: Developers
Classifier: Intended Audience :: Science/Research
Classifier: License :: DFSG approved
Classifier: License :: OSI Approved :: Apache Software License
Classifier: Operating System :: POSIX
Classifier: Programming Language :: Python
Classifier: Topic :: System :: Networking
Classifier: Topic :: System :: Distributed Computing
Classifier: Topic :: System :: Logging
Classifier: Topic :: System :: Monitoring
